{
    "Schedule": [
        {
            "Eventname": "Premium Pass - January 2025",
            "Eventdate": "Jan, 01 6am - Mar, 01 5am",
            "selection1": "25d 6h left"
        },
        {
            "Eventname": "Promo Pokédex - 40 Billion Card Celebration",
            "Eventdate": "Jan, 20 5pm - Apr, 30 4pm",
            "selection1": "85d 17h left"
        },
        {
            "Eventname": "McDonald’s × Pokémon Happy Meals Collaboration",
            "Eventdate": "Jan, 21 12am - Mar, 31 12am",
            "selection1": "55d 0h left"
        },
        {
            "Eventname": "Space-Time Smackdown Emblem Event",
            "Eventdate": "Feb, 04 6am - Feb, 25 5am",
            "selection1": "In 6h 37m"
        },
        {
            "Eventname": "Darkness-type Pokémon Mass Outbreak Event (Weavile ex)",
            "Eventdate": "Feb, 21 6am - Feb, 27 5am",
            "selection1": "In 17d 6h"
        },
        {
            "Eventname": "Cresselia ex Drop Event",
            "Eventdate": "Feb, 03 6am - Feb, 17 5am",
            "selection1": "13d 6h left"
        },
        {
            "Eventname": "Wonder Pick Event Part 1 (Chimchar + Togepi)",
            "Eventdate": "Feb, 07 6am - Feb, 21 5am",
            "selection1": "In 3d 6h"
        },
        {
            "Eventname": "Wonder Pick Event Part 2 (Chimchar + Togepi)",
            "Eventdate": "Feb, 14 6am - Feb, 21 5am",
            "selection1": "In 10d 6h"
        },
        {
            "Eventname": "Premium Pass - February 2025",
            "Eventdate": "Feb, 01 6am - Apr, 01 5am",
            "selection1": "56d 6h left"
        },
        {
            "Eventname": "Pokémon Day Celebration Gift",
            "Eventdate": "Feb, 27 2pm - Apr, 30 4pm",
            "selection1": "In 23d 14h"
        },
        {
            "Eventname": "Trade Feature Celebration Gift",
            "Eventdate": "Jan, 30 6am - Mar, 27 5am",
            "selection1": "51d 6h left"
        },
        {
            "Eventname": "Themed Booster Pack (A2a)",
            "Eventdate": "Feb, 28 6am - Dec, 31 6am",
            "selection1": "In 24d 6h"
        },
        {
            "Eventname": "Expansion (A3)",
            "Eventdate": "Apr, 30 6am - Dec, 31 6am",
            "selection1": "In 85d 6h"
        }
    ]
}