{
    "Tiers": [
        {
            "name": "Tier 1",
            "decks": [
                {
                    "name": "Buzzwole ex",
                    "image_url": "https://imgserv.pokemonmeta.com/v2/pkm/deck-type/Buzzwole%20ex?portrait=true&width=420 420w",
                    "power": "53.5",
                    "cards": [
                        {
                            "name": "Pheromosa",
                            "url": "https://s3.duellinksmeta.com/pkm_img/cards/682f264c11b021c3225af44f_w420.webp"
                        },
                        {
                            "name": "Kartana",
                            "url": "https://s3.duellinksmeta.com/pkm_img/cards/682f2690bcc5339033950d60_w420.webp"
                        },
                        {
                            "name": "Buzzwole ex",
                            "url": "https://s3.duellinksmeta.com/pkm_img/cards/682f25c711b021c3225af069_w420.webp"
                        },
                        {
                            "name": "Buzzwole ex",
                            "url": "https://s3.duellinksmeta.com/pkm_img/cards/682f25c711b021c3225af069_w420.webp"
                        },
                        {
                            "name": "Celesteela",
                            "url": "https://s3.duellinksmeta.com/pkm_img/cards/682f261811b021c3225af326_w420.webp"
                        },
                        {
                            "name": "Celesteela",
                            "url": "https://s3.duellinksmeta.com/pkm_img/cards/682f261811b021c3225af326_w420.webp"
                        },
                        {
                            "name": "Poké Ball",
                            "url": "https://s3.duellinksmeta.com/pkm_img/cards/672181a6c08874f5ab2e16f0_w420.webp"
                        },
                        {
                            "name": "Poké Ball",
                            "url": "https://s3.duellinksmeta.com/pkm_img/cards/672181a6c08874f5ab2e16f0_w420.webp"
                        },
                        {
                            "name": "Sabrina",
                            "url": "https://s3.duellinksmeta.com/pkm_img/cards/671ef0f25279bcfb3c1e25a3_w420.webp"
                        },
                        {
                            "name": "Professor's Research",
                            "url": "https://s3.duellinksmeta.com/pkm_img/cards/672181b7c08874f5ab2e1700_w420.webp"
                        },
                        {
                            "name": "Professor's Research",
                            "url": "https://s3.duellinksmeta.com/pkm_img/cards/672181b7c08874f5ab2e1700_w420.webp"
                        },
                        {
                            "name": "Pokémon Center Lady",
                            "url": "https://s3.duellinksmeta.com/pkm_img/cards/67e395a2575eceb838a249c9_w420.webp"
                        },
                        {
                            "name": "Mars",
                            "url": "https://s3.duellinksmeta.com/pkm_img/cards/6799bdfaf06a47c6afdf7d92_w420.webp"
                        },
                        {
                            "name": "Lusamine",
                            "url": "https://s3.duellinksmeta.com/pkm_img/cards/6837fd2b26d19a35a27b44bd_w420.webp"
                        },
                        {
                            "name": "Lusamine",
                            "url": "https://s3.duellinksmeta.com/pkm_img/cards/6837fd2b26d19a35a27b44bd_w420.webp"
                        },
                        {
                            "name": "Guzma",
                            "url": "https://s3.duellinksmeta.com/pkm_img/cards/6811cf73819c204fd6cdd872_w420.webp"
                        },
                        {
                            "name": "Erika",
                            "url": "https://s3.duellinksmeta.com/pkm_img/cards/671ef0f25279bcfb3c1e259d_w420.webp"
                        },
                        {
                            "name": "Cyrus",
                            "url": "https://s3.duellinksmeta.com/pkm_img/cards/6798ea0c6950657553dc675d_w420.webp"
                        },
                        {
                            "name": "Rocky Helmet",
                            "url": "https://s3.duellinksmeta.com/pkm_img/cards/6798e9cadbba2e0d2bb5f6a4_w420.webp"
                        },
                        {
                            "name": "Leaf Cape",
                            "url": "https://s3.duellinksmeta.com/pkm_img/cards/6811ceaaa93125d205b4cfb9_w420.webp"
                        }
                    ]
                }
            ]
        },
        {
            "name": "Tier 2",
            "decks": [
                {
                    "name": "Guzzlord ex",
                    "image_url": "https://imgserv.pokemonmeta.com/v2/pkm/deck-type/Guzzlord%20ex?portrait=true&width=420 420w",
                    "power": "28.5",
                    "cards": [
                        {
                            "name": "Nihilego",
                            "url": "https://s3.duellinksmeta.com/pkm_img/cards/682f262dbcc5339033950a9f_w420.webp"
                        },
                        {
                            "name": "Nihilego",
                            "url": "https://s3.duellinksmeta.com/pkm_img/cards/682f262dbcc5339033950a9f_w420.webp"
                        },
                        {
                            "name": "Guzzlord ex",
                            "url": "https://s3.duellinksmeta.com/pkm_img/cards/682f25b4bcc5339033950735_w420.webp"
                        },
                        {
                            "name": "Guzzlord ex",
                            "url": "https://s3.duellinksmeta.com/pkm_img/cards/682f25b4bcc5339033950735_w420.webp"
                        },
                        {
                            "name": "Celesteela",
                            "url": "https://s3.duellinksmeta.com/pkm_img/cards/682f261811b021c3225af326_w420.webp"
                        },
                        {
                            "name": "Celesteela",
                            "url": "https://s3.duellinksmeta.com/pkm_img/cards/682f261811b021c3225af326_w420.webp"
                        },
                        {
                            "name": "Poké Ball",
                            "url": "https://s3.duellinksmeta.com/pkm_img/cards/672181a6c08874f5ab2e16f0_w420.webp"
                        },
                        {
                            "name": "Poké Ball",
                            "url": "https://s3.duellinksmeta.com/pkm_img/cards/672181a6c08874f5ab2e16f0_w420.webp"
                        },
                        {
                            "name": "Sabrina",
                            "url": "https://s3.duellinksmeta.com/pkm_img/cards/671ef0f25279bcfb3c1e25a3_w420.webp"
                        },
                        {
                            "name": "Professor's Research",
                            "url": "https://s3.duellinksmeta.com/pkm_img/cards/672181b7c08874f5ab2e1700_w420.webp"
                        },
                        {
                            "name": "Professor's Research",
                            "url": "https://s3.duellinksmeta.com/pkm_img/cards/672181b7c08874f5ab2e1700_w420.webp"
                        },
                        {
                            "name": "Pokémon Center Lady",
                            "url": "https://s3.duellinksmeta.com/pkm_img/cards/67e395a2575eceb838a249c9_w420.webp"
                        },
                        {
                            "name": "Pokémon Center Lady",
                            "url": "https://s3.duellinksmeta.com/pkm_img/cards/67e395a2575eceb838a249c9_w420.webp"
                        },
                        {
                            "name": "Mars",
                            "url": "https://s3.duellinksmeta.com/pkm_img/cards/6799bdfaf06a47c6afdf7d92_w420.webp"
                        },
                        {
                            "name": "Lusamine",
                            "url": "https://s3.duellinksmeta.com/pkm_img/cards/6837fd2b26d19a35a27b44bd_w420.webp"
                        },
                        {
                            "name": "Lusamine",
                            "url": "https://s3.duellinksmeta.com/pkm_img/cards/6837fd2b26d19a35a27b44bd_w420.webp"
                        },
                        {
                            "name": "Cyrus",
                            "url": "https://s3.duellinksmeta.com/pkm_img/cards/6798ea0c6950657553dc675d_w420.webp"
                        },
                        {
                            "name": "Poison Barb",
                            "url": "https://s3.duellinksmeta.com/pkm_img/cards/6811ce7dc0a4ec0168e90349_w420.webp"
                        },
                        {
                            "name": "Poison Barb",
                            "url": "https://s3.duellinksmeta.com/pkm_img/cards/6811ce7dc0a4ec0168e90349_w420.webp"
                        },
                        {
                            "name": "Beastite",
                            "url": "https://s3.duellinksmeta.com/pkm_img/cards/6837fd844921a0b6650b38db_w420.webp"
                        }
                    ]
                },
                {
                    "name": "Silvally Rampardos",
                    "image_url": "https://imgserv.pokemonmeta.com/v2/pkm/deck-type/Silvally%20Rampardos?portrait=true&width=420 420w",
                    "power": "23.5",
                    "cards": [
                        {
                            "name": "Rampardos",
                            "url": "https://s3.duellinksmeta.com/pkm_img/cards/6799bb14169202e5d7e67d59_w420.webp"
                        },
                        {
                            "name": "Rampardos",
                            "url": "https://s3.duellinksmeta.com/pkm_img/cards/6799bb14169202e5d7e67d59_w420.webp"
                        },
                        {
                            "name": "Cranidos",
                            "url": "https://s3.duellinksmeta.com/pkm_img/cards/6799baf2169202e5d7e67c99_w420.webp"
                        },
                        {
                            "name": "Type: Null",
                            "url": "https://s3.duellinksmeta.com/pkm_img/cards/682f263c11b021c3225af409_w420.webp"
                        },
                        {
                            "name": "Type: Null",
                            "url": "https://s3.duellinksmeta.com/pkm_img/cards/682f263c11b021c3225af409_w420.webp"
                        },
                        {
                            "name": "Silvally",
                            "url": "https://s3.duellinksmeta.com/pkm_img/cards/6837fda726d19a35a27b48c5_w420.webp"
                        },
                        {
                            "name": "Silvally",
                            "url": "https://s3.duellinksmeta.com/pkm_img/cards/6837fda726d19a35a27b48c5_w420.webp"
                        },
                        {
                            "name": "Skull Fossil",
                            "url": "https://s3.duellinksmeta.com/pkm_img/cards/6799bcb5f06a47c6afdf7763_w420.webp"
                        },
                        {
                            "name": "Skull Fossil",
                            "url": "https://s3.duellinksmeta.com/pkm_img/cards/6799bcb5f06a47c6afdf7763_w420.webp"
                        },
                        {
                            "name": "Rare Candy",
                            "url": "https://s3.duellinksmeta.com/pkm_img/cards/680a3bcc8bc31f24c36ad483_w420.webp"
                        },
                        {
                            "name": "Rare Candy",
                            "url": "https://s3.duellinksmeta.com/pkm_img/cards/680a3bcc8bc31f24c36ad483_w420.webp"
                        },
                        {
                            "name": "Sabrina",
                            "url": "https://s3.duellinksmeta.com/pkm_img/cards/671ef0f25279bcfb3c1e25a3_w420.webp"
                        },
                        {
                            "name": "Red",
                            "url": "https://s3.duellinksmeta.com/pkm_img/cards/67e395dc575eceb838a24b19_w420.webp"
                        },
                        {
                            "name": "Professor's Research",
                            "url": "https://s3.duellinksmeta.com/pkm_img/cards/672181b7c08874f5ab2e1700_w420.webp"
                        },
                        {
                            "name": "Professor's Research",
                            "url": "https://s3.duellinksmeta.com/pkm_img/cards/672181b7c08874f5ab2e1700_w420.webp"
                        },
                        {
                            "name": "Mars",
                            "url": "https://s3.duellinksmeta.com/pkm_img/cards/6799bdfaf06a47c6afdf7d92_w420.webp"
                        },
                        {
                            "name": "Iono",
                            "url": "https://s3.duellinksmeta.com/pkm_img/cards/67dd67b3a1b6092a3c64b8b7_w420.webp"
                        },
                        {
                            "name": "Guzma",
                            "url": "https://s3.duellinksmeta.com/pkm_img/cards/6811cf73819c204fd6cdd872_w420.webp"
                        },
                        {
                            "name": "Gladion",
                            "url": "https://s3.duellinksmeta.com/pkm_img/cards/6837fd6826d19a35a27b469a_w420.webp"
                        },
                        {
                            "name": "Gladion",
                            "url": "https://s3.duellinksmeta.com/pkm_img/cards/6837fd6826d19a35a27b469a_w420.webp"
                        }
                    ]
                }
            ]
        },
        {
            "name": "Tier 3",
            "decks": [
                {
                    "name": "Solgaleo ex",
                    "image_url": "https://imgserv.pokemonmeta.com/v2/pkm/deck-type/Solgaleo%20ex?portrait=true&width=420 420w",
                    "power": "14.5",
                    "cards": [
                        {
                            "name": "Morelull",
                            "url": "https://s3.duellinksmeta.com/pkm_img/cards/675ae68b48e857c121990340_w420.webp"
                        },
                        {
                            "name": "Morelull",
                            "url": "https://s3.duellinksmeta.com/pkm_img/cards/675ae68b48e857c121990340_w420.webp"
                        },
                        {
                            "name": "Shiinotic",
                            "url": "https://s3.duellinksmeta.com/pkm_img/cards/6837fa7d26d19a35a27b30ba_w420.webp"
                        },
                        {
                            "name": "Shiinotic",
                            "url": "https://s3.duellinksmeta.com/pkm_img/cards/6837fa7d26d19a35a27b30ba_w420.webp"
                        },
                        {
                            "name": "Cosmog",
                            "url": "https://s3.duellinksmeta.com/pkm_img/cards/6811cae4c0a4ec0168e8e93c_w420.webp"
                        },
                        {
                            "name": "Cosmog",
                            "url": "https://s3.duellinksmeta.com/pkm_img/cards/6811cae4c0a4ec0168e8e93c_w420.webp"
                        },
                        {
                            "name": "Cosmoem",
                            "url": "https://s3.duellinksmeta.com/pkm_img/cards/6811cb7ac0a4ec0168e8ed4c_w420.webp"
                        },
                        {
                            "name": "Solgaleo ex",
                            "url": "https://s3.duellinksmeta.com/pkm_img/cards/680a3d40ee5adf8f1a257c25_w420.webp"
                        },
                        {
                            "name": "Solgaleo ex",
                            "url": "https://s3.duellinksmeta.com/pkm_img/cards/680a3d40ee5adf8f1a257c25_w420.webp"
                        },
                        {
                            "name": "Rare Candy",
                            "url": "https://s3.duellinksmeta.com/pkm_img/cards/680a3bcc8bc31f24c36ad483_w420.webp"
                        },
                        {
                            "name": "Rare Candy",
                            "url": "https://s3.duellinksmeta.com/pkm_img/cards/680a3bcc8bc31f24c36ad483_w420.webp"
                        },
                        {
                            "name": "Poké Ball",
                            "url": "https://s3.duellinksmeta.com/pkm_img/cards/672181a6c08874f5ab2e16f0_w420.webp"
                        },
                        {
                            "name": "Poké Ball",
                            "url": "https://s3.duellinksmeta.com/pkm_img/cards/672181a6c08874f5ab2e16f0_w420.webp"
                        },
                        {
                            "name": "Sabrina",
                            "url": "https://s3.duellinksmeta.com/pkm_img/cards/671ef0f25279bcfb3c1e25a3_w420.webp"
                        },
                        {
                            "name": "Professor's Research",
                            "url": "https://s3.duellinksmeta.com/pkm_img/cards/672181b7c08874f5ab2e1700_w420.webp"
                        },
                        {
                            "name": "Professor's Research",
                            "url": "https://s3.duellinksmeta.com/pkm_img/cards/672181b7c08874f5ab2e1700_w420.webp"
                        },
                        {
                            "name": "Mars",
                            "url": "https://s3.duellinksmeta.com/pkm_img/cards/6799bdfaf06a47c6afdf7d92_w420.webp"
                        },
                        {
                            "name": "Lillie",
                            "url": "https://s3.duellinksmeta.com/pkm_img/cards/6811d01f819c204fd6cddd25_w420.webp"
                        },
                        {
                            "name": "Guzma",
                            "url": "https://s3.duellinksmeta.com/pkm_img/cards/6811cf73819c204fd6cdd872_w420.webp"
                        },
                        {
                            "name": "Cyrus",
                            "url": "https://s3.duellinksmeta.com/pkm_img/cards/6798ea0c6950657553dc675d_w420.webp"
                        }
                    ]
                },
                {
                    "name": "Charizard ex",
                    "image_url": "https://imgserv.pokemonmeta.com/v2/pkm/deck-type/Charizard%20ex?portrait=true&width=420 420w",
                    "power": "13.0",
                    "cards": [
                        {
                            "name": "Charmeleon",
                            "url": "https://s3.duellinksmeta.com/pkm_img/cards/67e38f15575eceb838a2169b_w420.webp"
                        },
                        {
                            "name": "Charmeleon",
                            "url": "https://s3.duellinksmeta.com/pkm_img/cards/67e38f15575eceb838a2169b_w420.webp"
                        },
                        {
                            "name": "Charmander",
                            "url": "https://s3.duellinksmeta.com/pkm_img/cards/67e38ed6575eceb838a21501_w420.webp"
                        },
                        {
                            "name": "Charmander",
                            "url": "https://s3.duellinksmeta.com/pkm_img/cards/67e38ed6575eceb838a21501_w420.webp"
                        },
                        {
                            "name": "Type: Null",
                            "url": "https://s3.duellinksmeta.com/pkm_img/cards/682f263c11b021c3225af409_w420.webp"
                        },
                        {
                            "name": "Type: Null",
                            "url": "https://s3.duellinksmeta.com/pkm_img/cards/682f263c11b021c3225af409_w420.webp"
                        },
                        {
                            "name": "Silvally",
                            "url": "https://s3.duellinksmeta.com/pkm_img/cards/6837fda726d19a35a27b48c5_w420.webp"
                        },
                        {
                            "name": "Silvally",
                            "url": "https://s3.duellinksmeta.com/pkm_img/cards/6837fda726d19a35a27b48c5_w420.webp"
                        },
                        {
                            "name": "Rare Candy",
                            "url": "https://s3.duellinksmeta.com/pkm_img/cards/680a3bcc8bc31f24c36ad483_w420.webp"
                        },
                        {
                            "name": "Rare Candy",
                            "url": "https://s3.duellinksmeta.com/pkm_img/cards/680a3bcc8bc31f24c36ad483_w420.webp"
                        },
                        {
                            "name": "Pokémon Communication",
                            "url": "https://s3.duellinksmeta.com/pkm_img/cards/6799bd10169202e5d7e6885f_w420.webp"
                        },
                        {
                            "name": "Poké Ball",
                            "url": "https://s3.duellinksmeta.com/pkm_img/cards/672181a6c08874f5ab2e16f0_w420.webp"
                        },
                        {
                            "name": "Poké Ball",
                            "url": "https://s3.duellinksmeta.com/pkm_img/cards/672181a6c08874f5ab2e16f0_w420.webp"
                        },
                        {
                            "name": "Sabrina",
                            "url": "https://s3.duellinksmeta.com/pkm_img/cards/671ef0f25279bcfb3c1e25a3_w420.webp"
                        },
                        {
                            "name": "Professor's Research",
                            "url": "https://s3.duellinksmeta.com/pkm_img/cards/672181b7c08874f5ab2e1700_w420.webp"
                        },
                        {
                            "name": "Professor's Research",
                            "url": "https://s3.duellinksmeta.com/pkm_img/cards/672181b7c08874f5ab2e1700_w420.webp"
                        },
                        {
                            "name": "Mars",
                            "url": "https://s3.duellinksmeta.com/pkm_img/cards/6799bdfaf06a47c6afdf7d92_w420.webp"
                        },
                        {
                            "name": "Lillie",
                            "url": "https://s3.duellinksmeta.com/pkm_img/cards/6811d01f819c204fd6cddd25_w420.webp"
                        },
                        {
                            "name": "Gladion",
                            "url": "https://s3.duellinksmeta.com/pkm_img/cards/6837fd6826d19a35a27b469a_w420.webp"
                        },
                        {
                            "name": "Gladion",
                            "url": "https://s3.duellinksmeta.com/pkm_img/cards/6837fd6826d19a35a27b469a_w420.webp"
                        }
                    ]
                },
                {
                    "name": "Giratina ex Darkrai ex",
                    "image_url": "https://imgserv.pokemonmeta.com/v2/pkm/deck-type/Giratina%20ex%20Darkrai%20ex?portrait=true&width=420 420w",
                    "power": "13.0",
                    "cards": [
                        {
                            "name": "Giratina ex",
                            "url": "https://s3.duellinksmeta.com/pkm_img/cards/67dd6974e2096b41c50faf01_w420.webp"
                        },
                        {
                            "name": "Giratina ex",
                            "url": "https://s3.duellinksmeta.com/pkm_img/cards/67dd6974e2096b41c50faf01_w420.webp"
                        },
                        {
                            "name": "Nihilego",
                            "url": "https://s3.duellinksmeta.com/pkm_img/cards/682f262dbcc5339033950a9f_w420.webp"
                        },
                        {
                            "name": "Darkrai ex",
                            "url": "https://s3.duellinksmeta.com/pkm_img/cards/6799b936f06a47c6afdf6601_w420.webp"
                        },
                        {
                            "name": "Darkrai ex",
                            "url": "https://s3.duellinksmeta.com/pkm_img/cards/6799b936f06a47c6afdf6601_w420.webp"
                        },
                        {
                            "name": "Potion",
                            "url": "https://s3.duellinksmeta.com/pkm_img/cards/67216b665d66038af44d6d20_w420.webp"
                        },
                        {
                            "name": "Potion",
                            "url": "https://s3.duellinksmeta.com/pkm_img/cards/67216b665d66038af44d6d20_w420.webp"
                        },
                        {
                            "name": "Poké Ball",
                            "url": "https://s3.duellinksmeta.com/pkm_img/cards/672181a6c08874f5ab2e16f0_w420.webp"
                        },
                        {
                            "name": "Poké Ball",
                            "url": "https://s3.duellinksmeta.com/pkm_img/cards/672181a6c08874f5ab2e16f0_w420.webp"
                        },
                        {
                            "name": "Sabrina",
                            "url": "https://s3.duellinksmeta.com/pkm_img/cards/671ef0f25279bcfb3c1e25a3_w420.webp"
                        },
                        {
                            "name": "Professor's Research",
                            "url": "https://s3.duellinksmeta.com/pkm_img/cards/672181b7c08874f5ab2e1700_w420.webp"
                        },
                        {
                            "name": "Professor's Research",
                            "url": "https://s3.duellinksmeta.com/pkm_img/cards/672181b7c08874f5ab2e1700_w420.webp"
                        },
                        {
                            "name": "Pokémon Center Lady",
                            "url": "https://s3.duellinksmeta.com/pkm_img/cards/67e395a2575eceb838a249c9_w420.webp"
                        },
                        {
                            "name": "Pokémon Center Lady",
                            "url": "https://s3.duellinksmeta.com/pkm_img/cards/67e395a2575eceb838a249c9_w420.webp"
                        },
                        {
                            "name": "Guzma",
                            "url": "https://s3.duellinksmeta.com/pkm_img/cards/6811cf73819c204fd6cdd872_w420.webp"
                        },
                        {
                            "name": "Cyrus",
                            "url": "https://s3.duellinksmeta.com/pkm_img/cards/6798ea0c6950657553dc675d_w420.webp"
                        },
                        {
                            "name": "Poison Barb",
                            "url": "https://s3.duellinksmeta.com/pkm_img/cards/6811ce7dc0a4ec0168e90349_w420.webp"
                        },
                        {
                            "name": "Poison Barb",
                            "url": "https://s3.duellinksmeta.com/pkm_img/cards/6811ce7dc0a4ec0168e90349_w420.webp"
                        },
                        {
                            "name": "Giant Cape",
                            "url": "https://s3.duellinksmeta.com/pkm_img/cards/6798e48fb5fbced301dccc91_w420.webp"
                        },
                        {
                            "name": "Giant Cape",
                            "url": "https://s3.duellinksmeta.com/pkm_img/cards/6798e48fb5fbced301dccc91_w420.webp"
                        }
                    ]
                },
                {
                    "name": "Silvally",
                    "image_url": "https://imgserv.pokemonmeta.com/v2/pkm/deck-type/Silvally?portrait=true&width=420 420w",
                    "power": "12.5",
                    "cards": [
                        {
                            "name": "Zeraora",
                            "url": "https://s3.duellinksmeta.com/pkm_img/cards/682f272a11b021c3225afc1f_w420.webp"
                        },
                        {
                            "name": "Oricorio",
                            "url": "https://s3.duellinksmeta.com/pkm_img/cards/6811c4ebc0a4ec0168e8c1d1_w420.webp"
                        },
                        {
                            "name": "Oricorio",
                            "url": "https://s3.duellinksmeta.com/pkm_img/cards/6811c4ebc0a4ec0168e8c1d1_w420.webp"
                        },
                        {
                            "name": "Type: Null",
                            "url": "https://s3.duellinksmeta.com/pkm_img/cards/682f263c11b021c3225af409_w420.webp"
                        },
                        {
                            "name": "Type: Null",
                            "url": "https://s3.duellinksmeta.com/pkm_img/cards/682f263c11b021c3225af409_w420.webp"
                        },
                        {
                            "name": "Silvally",
                            "url": "https://s3.duellinksmeta.com/pkm_img/cards/6837fda726d19a35a27b48c5_w420.webp"
                        },
                        {
                            "name": "Silvally",
                            "url": "https://s3.duellinksmeta.com/pkm_img/cards/6837fda726d19a35a27b48c5_w420.webp"
                        },
                        {
                            "name": "Poké Ball",
                            "url": "https://s3.duellinksmeta.com/pkm_img/cards/672181a6c08874f5ab2e16f0_w420.webp"
                        },
                        {
                            "name": "Poké Ball",
                            "url": "https://s3.duellinksmeta.com/pkm_img/cards/672181a6c08874f5ab2e16f0_w420.webp"
                        },
                        {
                            "name": "Sabrina",
                            "url": "https://s3.duellinksmeta.com/pkm_img/cards/671ef0f25279bcfb3c1e25a3_w420.webp"
                        },
                        {
                            "name": "Professor's Research",
                            "url": "https://s3.duellinksmeta.com/pkm_img/cards/672181b7c08874f5ab2e1700_w420.webp"
                        },
                        {
                            "name": "Professor's Research",
                            "url": "https://s3.duellinksmeta.com/pkm_img/cards/672181b7c08874f5ab2e1700_w420.webp"
                        },
                        {
                            "name": "Mars",
                            "url": "https://s3.duellinksmeta.com/pkm_img/cards/6799bdfaf06a47c6afdf7d92_w420.webp"
                        },
                        {
                            "name": "Gladion",
                            "url": "https://s3.duellinksmeta.com/pkm_img/cards/6837fd6826d19a35a27b469a_w420.webp"
                        },
                        {
                            "name": "Gladion",
                            "url": "https://s3.duellinksmeta.com/pkm_img/cards/6837fd6826d19a35a27b469a_w420.webp"
                        },
                        {
                            "name": "Giovanni",
                            "url": "https://s3.duellinksmeta.com/pkm_img/cards/671ef0f25279bcfb3c1e25a1_w420.webp"
                        },
                        {
                            "name": "Dawn",
                            "url": "https://s3.duellinksmeta.com/pkm_img/cards/6799a5e0169202e5d7e614b9_w420.webp"
                        },
                        {
                            "name": "Cyrus",
                            "url": "https://s3.duellinksmeta.com/pkm_img/cards/6798ea0c6950657553dc675d_w420.webp"
                        },
                        {
                            "name": "Rocky Helmet",
                            "url": "https://s3.duellinksmeta.com/pkm_img/cards/6798e9cadbba2e0d2bb5f6a4_w420.webp"
                        },
                        {
                            "name": "Giant Cape",
                            "url": "https://s3.duellinksmeta.com/pkm_img/cards/6798e48fb5fbced301dccc91_w420.webp"
                        }
                    ]
                },
                {
                    "name": "Magnezone",
                    "image_url": "https://imgserv.pokemonmeta.com/v2/pkm/deck-type/Magnezone?portrait=true&width=420 420w",
                    "power": "7.0",
                    "cards": [
                        {
                            "name": "Shaymin",
                            "url": "https://s3.duellinksmeta.com/pkm_img/cards/6799b296169202e5d7e650f6_w420.webp"
                        },
                        {
                            "name": "Oricorio",
                            "url": "https://s3.duellinksmeta.com/pkm_img/cards/6811c4ebc0a4ec0168e8c1d1_w420.webp"
                        },
                        {
                            "name": "Oricorio",
                            "url": "https://s3.duellinksmeta.com/pkm_img/cards/6811c4ebc0a4ec0168e8c1d1_w420.webp"
                        },
                        {
                            "name": "Magnezone",
                            "url": "https://s3.duellinksmeta.com/pkm_img/cards/6799b5bff06a47c6afdf5344_w420.webp"
                        },
                        {
                            "name": "Magnezone",
                            "url": "https://s3.duellinksmeta.com/pkm_img/cards/6799b5bff06a47c6afdf5344_w420.webp"
                        },
                        {
                            "name": "Magneton",
                            "url": "https://s3.duellinksmeta.com/pkm_img/cards/671ef0f25279bcfb3c1e2524_w420.webp"
                        },
                        {
                            "name": "Magneton",
                            "url": "https://s3.duellinksmeta.com/pkm_img/cards/671ef0f25279bcfb3c1e2524_w420.webp"
                        },
                        {
                            "name": "Magnemite",
                            "url": "https://s3.duellinksmeta.com/pkm_img/cards/671ef0f25279bcfb3c1e2523_w420.webp"
                        },
                        {
                            "name": "Magnemite",
                            "url": "https://s3.duellinksmeta.com/pkm_img/cards/671ef0f25279bcfb3c1e2523_w420.webp"
                        },
                        {
                            "name": "Pokémon Communication",
                            "url": "https://s3.duellinksmeta.com/pkm_img/cards/6799bd10169202e5d7e6885f_w420.webp"
                        },
                        {
                            "name": "Poké Ball",
                            "url": "https://s3.duellinksmeta.com/pkm_img/cards/672181a6c08874f5ab2e16f0_w420.webp"
                        },
                        {
                            "name": "Poké Ball",
                            "url": "https://s3.duellinksmeta.com/pkm_img/cards/672181a6c08874f5ab2e16f0_w420.webp"
                        },
                        {
                            "name": "Sabrina",
                            "url": "https://s3.duellinksmeta.com/pkm_img/cards/671ef0f25279bcfb3c1e25a3_w420.webp"
                        },
                        {
                            "name": "Professor's Research",
                            "url": "https://s3.duellinksmeta.com/pkm_img/cards/672181b7c08874f5ab2e1700_w420.webp"
                        },
                        {
                            "name": "Professor's Research",
                            "url": "https://s3.duellinksmeta.com/pkm_img/cards/672181b7c08874f5ab2e1700_w420.webp"
                        },
                        {
                            "name": "Pokémon Center Lady",
                            "url": "https://s3.duellinksmeta.com/pkm_img/cards/67e395a2575eceb838a249c9_w420.webp"
                        },
                        {
                            "name": "Pokémon Center Lady",
                            "url": "https://s3.duellinksmeta.com/pkm_img/cards/67e395a2575eceb838a249c9_w420.webp"
                        },
                        {
                            "name": "Mars",
                            "url": "https://s3.duellinksmeta.com/pkm_img/cards/6799bdfaf06a47c6afdf7d92_w420.webp"
                        },
                        {
                            "name": "Cyrus",
                            "url": "https://s3.duellinksmeta.com/pkm_img/cards/6798ea0c6950657553dc675d_w420.webp"
                        },
                        {
                            "name": "Giant Cape",
                            "url": "https://s3.duellinksmeta.com/pkm_img/cards/6798e48fb5fbced301dccc91_w420.webp"
                        }
                    ]
                },
                {
                    "name": "Giratina ex Greninja",
                    "image_url": "https://imgserv.pokemonmeta.com/v2/pkm/deck-type/Giratina%20ex%20Greninja?portrait=true&width=420 420w",
                    "power": "6.0",
                    "cards": [
                        {
                            "name": "Pyukumuku",
                            "url": "https://s3.duellinksmeta.com/pkm_img/cards/6811c3c7a93125d205b48622_w420.webp"
                        },
                        {
                            "name": "Pyukumuku",
                            "url": "https://s3.duellinksmeta.com/pkm_img/cards/6811c3c7a93125d205b48622_w420.webp"
                        },
                        {
                            "name": "Greninja",
                            "url": "https://s3.duellinksmeta.com/pkm_img/cards/671ef0f25279bcfb3c1e251b_w420.webp"
                        },
                        {
                            "name": "Greninja",
                            "url": "https://s3.duellinksmeta.com/pkm_img/cards/671ef0f25279bcfb3c1e251b_w420.webp"
                        },
                        {
                            "name": "Frogadier",
                            "url": "https://s3.duellinksmeta.com/pkm_img/cards/671ef0f25279bcfb3c1e251a_w420.webp"
                        },
                        {
                            "name": "Froakie",
                            "url": "https://s3.duellinksmeta.com/pkm_img/cards/671ef0f25279bcfb3c1e2519_w420.webp"
                        },
                        {
                            "name": "Froakie",
                            "url": "https://s3.duellinksmeta.com/pkm_img/cards/671ef0f25279bcfb3c1e2519_w420.webp"
                        },
                        {
                            "name": "Giratina ex",
                            "url": "https://s3.duellinksmeta.com/pkm_img/cards/67dd6974e2096b41c50faf01_w420.webp"
                        },
                        {
                            "name": "Giratina ex",
                            "url": "https://s3.duellinksmeta.com/pkm_img/cards/67dd6974e2096b41c50faf01_w420.webp"
                        },
                        {
                            "name": "Rare Candy",
                            "url": "https://s3.duellinksmeta.com/pkm_img/cards/680a3bcc8bc31f24c36ad483_w420.webp"
                        },
                        {
                            "name": "Rare Candy",
                            "url": "https://s3.duellinksmeta.com/pkm_img/cards/680a3bcc8bc31f24c36ad483_w420.webp"
                        },
                        {
                            "name": "Pokémon Communication",
                            "url": "https://s3.duellinksmeta.com/pkm_img/cards/6799bd10169202e5d7e6885f_w420.webp"
                        },
                        {
                            "name": "Poké Ball",
                            "url": "https://s3.duellinksmeta.com/pkm_img/cards/672181a6c08874f5ab2e16f0_w420.webp"
                        },
                        {
                            "name": "Poké Ball",
                            "url": "https://s3.duellinksmeta.com/pkm_img/cards/672181a6c08874f5ab2e16f0_w420.webp"
                        },
                        {
                            "name": "Professor's Research",
                            "url": "https://s3.duellinksmeta.com/pkm_img/cards/672181b7c08874f5ab2e1700_w420.webp"
                        },
                        {
                            "name": "Professor's Research",
                            "url": "https://s3.duellinksmeta.com/pkm_img/cards/672181b7c08874f5ab2e1700_w420.webp"
                        },
                        {
                            "name": "Pokémon Center Lady",
                            "url": "https://s3.duellinksmeta.com/pkm_img/cards/67e395a2575eceb838a249c9_w420.webp"
                        },
                        {
                            "name": "Mars",
                            "url": "https://s3.duellinksmeta.com/pkm_img/cards/6799bdfaf06a47c6afdf7d92_w420.webp"
                        },
                        {
                            "name": "Cyrus",
                            "url": "https://s3.duellinksmeta.com/pkm_img/cards/6798ea0c6950657553dc675d_w420.webp"
                        },
                        {
                            "name": "Cyrus",
                            "url": "https://s3.duellinksmeta.com/pkm_img/cards/6798ea0c6950657553dc675d_w420.webp"
                        }
                    ]
                },
                {
                    "name": "Zeraora",
                    "image_url": "https://imgserv.pokemonmeta.com/v2/pkm/deck-type/Zeraora?portrait=true&width=420 420w",
                    "power": "5.0",
                    "cards": [
                        {
                            "name": "Zeraora",
                            "url": "https://s3.duellinksmeta.com/pkm_img/cards/682f272a11b021c3225afc1f_w420.webp"
                        },
                        {
                            "name": "Zeraora",
                            "url": "https://s3.duellinksmeta.com/pkm_img/cards/682f272a11b021c3225afc1f_w420.webp"
                        },
                        {
                            "name": "Oricorio",
                            "url": "https://s3.duellinksmeta.com/pkm_img/cards/6811c4ebc0a4ec0168e8c1d1_w420.webp"
                        },
                        {
                            "name": "Type: Null",
                            "url": "https://s3.duellinksmeta.com/pkm_img/cards/682f263c11b021c3225af409_w420.webp"
                        },
                        {
                            "name": "Type: Null",
                            "url": "https://s3.duellinksmeta.com/pkm_img/cards/682f263c11b021c3225af409_w420.webp"
                        },
                        {
                            "name": "Silvally",
                            "url": "https://s3.duellinksmeta.com/pkm_img/cards/6837fda726d19a35a27b48c5_w420.webp"
                        },
                        {
                            "name": "Silvally",
                            "url": "https://s3.duellinksmeta.com/pkm_img/cards/6837fda726d19a35a27b48c5_w420.webp"
                        },
                        {
                            "name": "Poké Ball",
                            "url": "https://s3.duellinksmeta.com/pkm_img/cards/672181a6c08874f5ab2e16f0_w420.webp"
                        },
                        {
                            "name": "Poké Ball",
                            "url": "https://s3.duellinksmeta.com/pkm_img/cards/672181a6c08874f5ab2e16f0_w420.webp"
                        },
                        {
                            "name": "Sabrina",
                            "url": "https://s3.duellinksmeta.com/pkm_img/cards/671ef0f25279bcfb3c1e25a3_w420.webp"
                        },
                        {
                            "name": "Professor's Research",
                            "url": "https://s3.duellinksmeta.com/pkm_img/cards/672181b7c08874f5ab2e1700_w420.webp"
                        },
                        {
                            "name": "Professor's Research",
                            "url": "https://s3.duellinksmeta.com/pkm_img/cards/672181b7c08874f5ab2e1700_w420.webp"
                        },
                        {
                            "name": "Pokémon Center Lady",
                            "url": "https://s3.duellinksmeta.com/pkm_img/cards/67e395a2575eceb838a249c9_w420.webp"
                        },
                        {
                            "name": "Mars",
                            "url": "https://s3.duellinksmeta.com/pkm_img/cards/6799bdfaf06a47c6afdf7d92_w420.webp"
                        },
                        {
                            "name": "Gladion",
                            "url": "https://s3.duellinksmeta.com/pkm_img/cards/6837fd6826d19a35a27b469a_w420.webp"
                        },
                        {
                            "name": "Gladion",
                            "url": "https://s3.duellinksmeta.com/pkm_img/cards/6837fd6826d19a35a27b469a_w420.webp"
                        },
                        {
                            "name": "Giovanni",
                            "url": "https://s3.duellinksmeta.com/pkm_img/cards/671ef0f25279bcfb3c1e25a1_w420.webp"
                        },
                        {
                            "name": "Dawn",
                            "url": "https://s3.duellinksmeta.com/pkm_img/cards/6799a5e0169202e5d7e614b9_w420.webp"
                        },
                        {
                            "name": "Cyrus",
                            "url": "https://s3.duellinksmeta.com/pkm_img/cards/6798ea0c6950657553dc675d_w420.webp"
                        },
                        {
                            "name": "Giant Cape",
                            "url": "https://s3.duellinksmeta.com/pkm_img/cards/6798e48fb5fbced301dccc91_w420.webp"
                        }
                    ]
                }
            ]
        },
        {
            "name": "Trending",
            "decks": [
                {
                    "name": "Palkia ex Manaphy",
                    "image_url": "https://imgserv.pokemonmeta.com/v2/pkm/deck-type/Palkia%20ex%20Manaphy?portrait=true&width=420 420w",
                    "power": "3.0",
                    "cards": [
                        {
                            "name": "Palkia ex",
                            "url": "https://s3.duellinksmeta.com/pkm_img/cards/6799b5ddf06a47c6afdf53ce_w420.webp"
                        },
                        {
                            "name": "Palkia ex",
                            "url": "https://s3.duellinksmeta.com/pkm_img/cards/6799b5ddf06a47c6afdf53ce_w420.webp"
                        },
                        {
                            "name": "Manaphy",
                            "url": "https://s3.duellinksmeta.com/pkm_img/cards/6799b628f06a47c6afdf561c_w420.webp"
                        },
                        {
                            "name": "Manaphy",
                            "url": "https://s3.duellinksmeta.com/pkm_img/cards/6799b628f06a47c6afdf561c_w420.webp"
                        },
                        {
                            "name": "Type: Null",
                            "url": "https://s3.duellinksmeta.com/pkm_img/cards/682f263c11b021c3225af409_w420.webp"
                        },
                        {
                            "name": "Type: Null",
                            "url": "https://s3.duellinksmeta.com/pkm_img/cards/682f263c11b021c3225af409_w420.webp"
                        },
                        {
                            "name": "Silvally",
                            "url": "https://s3.duellinksmeta.com/pkm_img/cards/6837fda726d19a35a27b48c5_w420.webp"
                        },
                        {
                            "name": "Silvally",
                            "url": "https://s3.duellinksmeta.com/pkm_img/cards/6837fda726d19a35a27b48c5_w420.webp"
                        },
                        {
                            "name": "Poké Ball",
                            "url": "https://s3.duellinksmeta.com/pkm_img/cards/672181a6c08874f5ab2e16f0_w420.webp"
                        },
                        {
                            "name": "Poké Ball",
                            "url": "https://s3.duellinksmeta.com/pkm_img/cards/672181a6c08874f5ab2e16f0_w420.webp"
                        },
                        {
                            "name": "Sabrina",
                            "url": "https://s3.duellinksmeta.com/pkm_img/cards/671ef0f25279bcfb3c1e25a3_w420.webp"
                        },
                        {
                            "name": "Professor's Research",
                            "url": "https://s3.duellinksmeta.com/pkm_img/cards/672181b7c08874f5ab2e1700_w420.webp"
                        },
                        {
                            "name": "Professor's Research",
                            "url": "https://s3.duellinksmeta.com/pkm_img/cards/672181b7c08874f5ab2e1700_w420.webp"
                        },
                        {
                            "name": "Misty",
                            "url": "https://s3.duellinksmeta.com/pkm_img/cards/671ef0f25279bcfb3c1e259e_w420.webp"
                        },
                        {
                            "name": "Misty",
                            "url": "https://s3.duellinksmeta.com/pkm_img/cards/671ef0f25279bcfb3c1e259e_w420.webp"
                        },
                        {
                            "name": "Mars",
                            "url": "https://s3.duellinksmeta.com/pkm_img/cards/6799bdfaf06a47c6afdf7d92_w420.webp"
                        },
                        {
                            "name": "Leaf",
                            "url": "https://s3.duellinksmeta.com/pkm_img/cards/675ae88248e857c1219910f6_w420.webp"
                        },
                        {
                            "name": "Gladion",
                            "url": "https://s3.duellinksmeta.com/pkm_img/cards/6837fd6826d19a35a27b469a_w420.webp"
                        },
                        {
                            "name": "Gladion",
                            "url": "https://s3.duellinksmeta.com/pkm_img/cards/6837fd6826d19a35a27b469a_w420.webp"
                        },
                        {
                            "name": "Giant Cape",
                            "url": "https://s3.duellinksmeta.com/pkm_img/cards/6798e48fb5fbced301dccc91_w420.webp"
                        }
                    ]
                },
                {
                    "name": "Gengar ex",
                    "image_url": "https://imgserv.pokemonmeta.com/v2/pkm/deck-type/Gengar%20ex?portrait=true&width=420 420w",
                    "power": "2.0",
                    "cards": [
                        {
                            "name": "Shiinotic",
                            "url": "https://s3.duellinksmeta.com/pkm_img/cards/6837fa7d26d19a35a27b30ba_w420.webp"
                        },
                        {
                            "name": "Shiinotic",
                            "url": "https://s3.duellinksmeta.com/pkm_img/cards/6837fa7d26d19a35a27b30ba_w420.webp"
                        },
                        {
                            "name": "Morelull",
                            "url": "https://s3.duellinksmeta.com/pkm_img/cards/6837fa5926d19a35a27b2ff2_w420.webp"
                        },
                        {
                            "name": "Morelull",
                            "url": "https://s3.duellinksmeta.com/pkm_img/cards/6837fa5926d19a35a27b2ff2_w420.webp"
                        },
                        {
                            "name": "Haunter",
                            "url": "https://s3.duellinksmeta.com/pkm_img/cards/671ef0f25279bcfb3c1e253b_w420.webp"
                        },
                        {
                            "name": "Gengar ex",
                            "url": "https://s3.duellinksmeta.com/pkm_img/cards/671ef0f25279bcfb3c1e253d_w420.webp"
                        },
                        {
                            "name": "Gengar ex",
                            "url": "https://s3.duellinksmeta.com/pkm_img/cards/671ef0f25279bcfb3c1e253d_w420.webp"
                        },
                        {
                            "name": "Gengar",
                            "url": "https://s3.duellinksmeta.com/pkm_img/cards/671ef0f25279bcfb3c1e253c_w420.webp"
                        },
                        {
                            "name": "Gastly",
                            "url": "https://s3.duellinksmeta.com/pkm_img/cards/671ef0f25279bcfb3c1e253a_w420.webp"
                        },
                        {
                            "name": "Gastly",
                            "url": "https://s3.duellinksmeta.com/pkm_img/cards/671ef0f25279bcfb3c1e253a_w420.webp"
                        },
                        {
                            "name": "Rare Candy",
                            "url": "https://s3.duellinksmeta.com/pkm_img/cards/680a3bcc8bc31f24c36ad483_w420.webp"
                        },
                        {
                            "name": "Rare Candy",
                            "url": "https://s3.duellinksmeta.com/pkm_img/cards/680a3bcc8bc31f24c36ad483_w420.webp"
                        },
                        {
                            "name": "Poké Ball",
                            "url": "https://s3.duellinksmeta.com/pkm_img/cards/672181a6c08874f5ab2e16f0_w420.webp"
                        },
                        {
                            "name": "Poké Ball",
                            "url": "https://s3.duellinksmeta.com/pkm_img/cards/672181a6c08874f5ab2e16f0_w420.webp"
                        },
                        {
                            "name": "Professor's Research",
                            "url": "https://s3.duellinksmeta.com/pkm_img/cards/672181b7c08874f5ab2e1700_w420.webp"
                        },
                        {
                            "name": "Professor's Research",
                            "url": "https://s3.duellinksmeta.com/pkm_img/cards/672181b7c08874f5ab2e1700_w420.webp"
                        },
                        {
                            "name": "Lillie",
                            "url": "https://s3.duellinksmeta.com/pkm_img/cards/6811d01f819c204fd6cddd25_w420.webp"
                        },
                        {
                            "name": "Lillie",
                            "url": "https://s3.duellinksmeta.com/pkm_img/cards/6811d01f819c204fd6cddd25_w420.webp"
                        },
                        {
                            "name": "Cyrus",
                            "url": "https://s3.duellinksmeta.com/pkm_img/cards/6798ea0c6950657553dc675d_w420.webp"
                        },
                        {
                            "name": "Celestic Town Elder",
                            "url": "https://s3.duellinksmeta.com/pkm_img/cards/67c1611ce06d5e18c00aec44_w420.webp"
                        }
                    ]
                }
            ]
        }
    ]
}